manimera/__init__.py
manimera/animations/__init__.py
manimera/animations/advance_clock_time.py
manimera/animations/atom_rotate.py
manimera/animations/fade_reveal.py
manimera/animations/lamp_glow.py
manimera/animations/pendulum_oscillation.py
manimera/cli/__init__.py
manimera/cli/chapter.py
manimera/cli/main.py
manimera/cli/project.py
manimera/cli/scene.py
manimera/cli/templates.py
manimera/cli/utils.py
manimera/cli/workflow.py
manimera/components/__init__.py
manimera/components/anatomical_eye.py
manimera/components/atomic_clock.py
manimera/components/bohr_atom.py
manimera/components/brick.py
manimera/components/cathedral_lamp.py
manimera/components/clock.py
manimera/components/feather.py
manimera/components/network_tower.py
manimera/components/pendulum.py
manimera/components/silhouette.py
manimera/components/logic_gates/__init__.py
manimera/components/logic_gates/base.py
manimera/components/logic_gates/wire.py
manimera/components/logic_gates/conjunction/__init__.py
manimera/components/logic_gates/conjunction/and_gate.py
manimera/components/logic_gates/conjunction/base.py
manimera/components/logic_gates/conjunction/nand_gate.py
manimera/components/logic_gates/disjunction/__init__.py
manimera/components/logic_gates/disjunction/base.py
manimera/components/logic_gates/disjunction/nor_gate.py
manimera/components/logic_gates/disjunction/or_gate.py
manimera/components/logic_gates/disjunction/xnor_gate.py
manimera/components/logic_gates/disjunction/xor_gate.py
manimera/components/logic_gates/layout/__init__.py
manimera/components/logic_gates/layout/input_manager.py
manimera/components/logic_gates/layout/sugiyama.py
manimera/components/logic_gates/unary/__init__.py
manimera/components/logic_gates/unary/base.py
manimera/components/logic_gates/unary/buffer_gate.py
manimera/components/logic_gates/unary/not_gate.py
manimera/components/logic_gates/unary/void_gate.py
manimera/constants/__init__.py
manimera/constants/science/__init__.py
manimera/constants/science/atom_type.py
manimera-0.5.5.dist-info/licenses/LICENSE
manimera-0.5.5.dist-info/METADATA
manimera-0.5.5.dist-info/WHEEL
manimera-0.5.5.dist-info/entry_points.txt
manimera-0.5.5.dist-info/top_level.txt
manimera-0.5.5.dist-info/RECORD
