Metadata-Version: 2.4
Name: manimera
Version: 0.5.5
Summary: Manimera is a Python library that makes creating Manim animations easy and fast. Designed for educators, content creators, and anyone making educational videos, Manimera provides a simple interface to animate mathematical concepts, graphics, and visual explanations without a lot of boilerplate code.
Requires-Python: >=3.13
License-File: LICENSE
Requires-Dist: dotenv>=0.9.9
Requires-Dist: manim>=0.19.1
Requires-Dist: rich>=14.2.0
Dynamic: license-file
